{"cameraMode":{"drawMode":0,"name":"Shaded","section":"Shading Mode"},"sceneLighting":true,"audioPlay":false,"sceneViewState":{"m_AlwaysRefresh":false,"showFog":true,"showSkybox":true,"showFlares":true,"showImageEffects":true,"showParticleSystems":true,"showVisualEffectGraphs":true,"m_FxEnabled":true},"in2DMode":false,"pivot":{"x":72.68421936035156,"y":-2.832587718963623,"z":18.4710693359375},"rotation":{"x":-0.14228947460651399,"y":-0.02198864333331585,"z":0.0031688138842582704,"w":-0.9895837306976318},"size":10.0,"orthographic":false}